InSearch/BM24.py
InSearch/BM25.py
InSearch/InSearch.py
InSearch/TokenAnalyzer.py
InSearch/__init__.py
InSearch-0.1.4.dist-info/METADATA
InSearch-0.1.4.dist-info/WHEEL
InSearch-0.1.4.dist-info/top_level.txt
InSearch-0.1.4.dist-info/RECORD
